root_painter_cli/__init__.py
root_painter_cli/main.py
root_painter-0.1.9.dist-info/WHEEL
root_painter-0.1.9.dist-info/entry_points.txt
root_painter-0.1.9.dist-info/METADATA
root_painter-0.1.9.dist-info/RECORD
