Metadata-Version: 2.4
Name: root-painter
Version: 0.1.9
Summary: RootPainter GUI and trainer packaged as a single CLI
License-Expression: GPL-3.0-or-later
Requires-Dist: root-painter-painter
Requires-Dist: typer>=0.16.1
Requires-Dist: root-painter-trainer ; extra == 'trainer'
Requires-Python: >=3.10, <3.12
Provides-Extra: trainer
